tl2/__init__.py
tl2/tl2_utils.py
tl2/imagenet/imagenet_utils.py
tl2/imagenet/map_subdir_id_name.txt
tl2/launch/launch_utils.py
tl2/launch/configs/Launch_v1.yaml
tl2/launch/scripts/run_ddp.py
tl2/launch/tests/test_launch.py
tl2/modelarts/__init__.py
tl2/modelarts/modelarts_utils.py
tl2/modelarts/moxing_utils.py
tl2/modelarts/configs/run.yaml
tl2/modelarts/scripts/copy_file_list.py
tl2/modelarts/scripts/copy_tool.py
tl2/modelarts/scripts/make_log_dirs.py
tl2/modelarts/scripts/plot_results_obs.py
tl2/modelarts/scripts/run.py
tl2/modelarts/scripts/run.sh
tl2/modelarts/scripts/run_v2_modelarts.sh
tl2/modelarts/scripts/s3_downloader.py
tl2/modelarts/scripts/s3_uploader.py
tl2/modelarts/scripts/setup_env.sh
tl2/modelarts/scripts/setup_env_debug.sh
tl2/modelarts/scripts/start_modelarts_v2.py
tl2/modelarts/scripts/test_bash.py
tl2/modelarts/scripts/test_bash.sh
tl2/modelarts/scripts/test_resnet.py
tl2/modelarts/sources/pip.conf.modelarts
tl2/modelarts/sources/sources.list.modelarts
tl2/modelarts/tests/test_run.py
tl2/proj/__init__.py
tl2/proj/GAN/eval_FID_given_imgdir.py
tl2/proj/GAN/frequency_spectrum.py
tl2/proj/GAN/plot_freq_spectrum.py
tl2/proj/argparser/argparser_utils.py
tl2/proj/cv2/cv2_utils.py
tl2/proj/dlib/__init__.py
tl2/proj/dlib/dlib_utils.py
tl2/proj/dlib/configs/dlib_web.yaml
tl2/proj/dlib/datasets/dlib_landmarks_68.png
tl2/proj/dlib/datasets/hand_convex_hull.jpg
tl2/proj/dlib/datasets/raw_face_list.txt
tl2/proj/dlib/datasets/raw_face/21242213255_abde1622df_o.jpg
tl2/proj/dlib/datasets/raw_face/heben1.jfif
tl2/proj/dlib/datasets/raw_face/korean1.jpeg
tl2/proj/dlib/datasets/raw_face/lecun1.png
tl2/proj/dlib/datasets/raw_face/liudehua1.jfif
tl2/proj/dlib/datasets/raw_face/nanmingxing3.jfif
tl2/proj/dlib/datasets/raw_face/peng.jpg
tl2/proj/dlib/datasets/raw_face/xiangnong1.jpeg
tl2/proj/dlib/datasets/raw_face/xinhengjieyi2.jpg
tl2/proj/dlib/ffhq_face_align/__init__.py
tl2/proj/dlib/ffhq_face_align/align_face_stmodel.py
tl2-0.1.2.dist-info/LICENSE
tl2-0.1.2.dist-info/METADATA
tl2-0.1.2.dist-info/WHEEL
tl2-0.1.2.dist-info/top_level.txt
tl2-0.1.2.dist-info/RECORD
