Metadata-Version: 2.1
Name: tl2
Version: 0.1.2
Summary: A personal package for research
Home-page: https://github.com/PeterouZh/tl2
Author: Peterou
Author-email: pengzhoucv@gmail.com
Classifier: Programming Language :: Python :: 3
Classifier: License :: OSI Approved :: MIT License
Classifier: Operating System :: OS Independent
License-File: LICENSE
Requires-Dist: easydict
Requires-Dist: termcolor
Requires-Dist: deepdiff
Requires-Dist: fvcore
Requires-Dist: numpy
Requires-Dist: matplotlib
Requires-Dist: pyyaml
Requires-Dist: omegaconf
Requires-Dist: einops
Requires-Dist: imageio-ffmpeg
Requires-Dist: opencv-python
Requires-Dist: scikit-image
Requires-Dist: tyro
